TBot/__init__.py
TBot/example.py
TBot/tbot.py
Alby7503TBot-1.0.9.dist-info/LICENSE
Alby7503TBot-1.0.9.dist-info/METADATA
Alby7503TBot-1.0.9.dist-info/WHEEL
Alby7503TBot-1.0.9.dist-info/top_level.txt
Alby7503TBot-1.0.9.dist-info/RECORD
