Metadata-Version: 2.1
Name: Alby7503TBot
Version: 1.0.9
Summary: Lightweight telegram bot library.
Home-page: https://github.com/Alby7503/TBot
Author: Alberto Vona
Author-email: alberto.vona24@gmail.com
License: GNU AGPLv3
Platform: UNKNOWN
Classifier: Programming Language :: Python :: 3
Classifier: License :: OSI Approved :: GNU Affero General Public License v3 or later (AGPLv3+)
Classifier: Operating System :: OS Independent
Requires-Python: >=3.6
